blisswriter/__init__.py
blisswriter/session_api.py
blisswriter/app/__init__.py
blisswriter/app/process.py
blisswriter/app/register_service.py
blisswriter/app/service.py
blisswriter/app/utils.py
blisswriter/io/__init__.py
blisswriter/io/h5_config.py
blisswriter/io/h5_external.py
blisswriter/io/io_utils.py
blisswriter/io/nexus.py
blisswriter/io/os_utils.py
blisswriter/nexus/__init__.py
blisswriter/nexus/devices.py
blisswriter/nexus/mapping.py
blisswriter/nexus/publish.py
blisswriter/nexus/scan_meta.py
blisswriter/parameters/__init__.py
blisswriter/parameters/base.py
blisswriter/parameters/config.py
blisswriter/patching/__init__.py
blisswriter/patching/monkey.py
blisswriter/patching/patch_h5py.py
blisswriter/patching/patch_isinstance.py
blisswriter/patching/patch_open.py
blisswriter/patching/patch_std.py
blisswriter/subscribers/__init__.py
blisswriter/subscribers/base_subscriber.py
blisswriter/subscribers/scan_subscriber.py
blisswriter/subscribers/session_subscriber.py
blisswriter/tango/__init__.py
blisswriter/tango/servers/NexusWriter.py
blisswriter/tango/servers/__init__.py
blisswriter/tests/__init__.py
blisswriter/tests/test_array_order.py
blisswriter/tests/test_base_subscriber.py
blisswriter/tests/test_data_merging.py
blisswriter/tests/test_dataset_proxy.py
blisswriter/tests/test_devices.py
blisswriter/tests/test_h5_external.py
blisswriter/tests/test_logging.py
blisswriter/tests/test_nexus.py
blisswriter/tests/test_reference_proxy.py
blisswriter/tests/test_rotating_file.py
blisswriter/tests/test_sync_utils.py
blisswriter/tests/helpers/__init__.py
blisswriter/tests/helpers/nxw_test_math.py
blisswriter/utils/__init__.py
blisswriter/utils/array_order.py
blisswriter/utils/array_size.py
blisswriter/utils/config_utils.py
blisswriter/utils/data_merging.py
blisswriter/utils/data_policy.py
blisswriter/utils/exceptions.py
blisswriter/utils/log_levels.py
blisswriter/utils/logging_utils.py
blisswriter/utils/patch_testing.py
blisswriter/utils/periodic.py
blisswriter-2.0.0.dist-info/licenses/LICENSE
blisswriter-2.0.0.dist-info/METADATA
blisswriter-2.0.0.dist-info/WHEEL
blisswriter-2.0.0.dist-info/entry_points.txt
blisswriter-2.0.0.dist-info/top_level.txt
blisswriter-2.0.0.dist-info/RECORD
