Metadata-Version: 2.4
Name: blisswriter
Version: 2.0.0
Summary: Bliss NeXus-compliant HDF5 file writer
Home-page: https://gitlab.esrf.fr/bliss/bliss/-/tree/master/blisswriter
Author: BCU (ESRF)
License: LGPLv3
Project-URL: Source, https://gitlab.esrf.fr/bliss/bliss/-/tree/master/blisswriter
Project-URL: Documentation, https://bliss.gitlab-pages.esrf.fr/bliss/
Project-URL: Tracker, https://gitlab.esrf.fr/bliss/bliss/issues/
Classifier: Intended Audience :: Science/Research
Classifier: License :: OSI Approved :: GNU Lesser General Public License v3 (LGPLv3)
Classifier: Programming Language :: Python :: 3
Requires-Python: >=3.7
License-File: LICENSE
Requires-Dist: blissdata<3,>=2
Requires-Dist: psutil
Requires-Dist: pyicat-plus
Requires-Dist: querypool
Provides-Extra: tango
Requires-Dist: blissdata[tango]; extra == "tango"
Provides-Extra: test
Requires-Dist: blissdata[tango]; extra == "test"
Requires-Dist: gevent; extra == "test"
Requires-Dist: hdf5plugin; extra == "test"
Requires-Dist: pytest>=7; extra == "test"
Provides-Extra: dev
Requires-Dist: blissdata[tango]; extra == "dev"
Requires-Dist: gevent; extra == "dev"
Requires-Dist: hdf5plugin; extra == "dev"
Requires-Dist: pytest>=7; extra == "dev"
Requires-Dist: black>=22; extra == "dev"
Requires-Dist: flake8>=4; extra == "dev"
Dynamic: license-file
